samplics/__init__.py
samplics/py.typed
samplics/apis/__init__.py
samplics/apis/compare.py
samplics/apis/fit.py
samplics/apis/predict.py
samplics/apis/validate.py
samplics/apis/base/__init__.py
samplics/apis/base/fitting.py
samplics/apis/sae/__init__.py
samplics/apis/sae/area_eblup.py
samplics/apis/sampling/__init__.py
samplics/apis/sampling/core.py
samplics/apis/sampling/frame.py
samplics/apis/sampling/sample.py
samplics/categorical/__init__.py
samplics/categorical/comparison.py
samplics/categorical/tabulation.py
samplics/categorical/tabulation_old.py
samplics/datasets/__init__.py
samplics/datasets/datasets.py
samplics/datasets/data/auto.csv
samplics/datasets/data/birth.csv
samplics/datasets/data/countycrop.csv
samplics/datasets/data/countycrop_means.csv
samplics/datasets/data/expenditure_on_milk.csv
samplics/datasets/data/nhanes2.csv
samplics/datasets/data/nhanes2brr_subset.csv
samplics/datasets/data/nhanes2jk_subset.csv
samplics/datasets/data/nmihs_subset.csv
samplics/datasets/data/psu_frame.csv
samplics/datasets/data/psu_sample.csv
samplics/datasets/data/ssu_sample.csv
samplics/estimation/__init__.py
samplics/estimation/calibration.py
samplics/estimation/expansion.py
samplics/estimation/replication.py
samplics/regression/__init__.py
samplics/regression/glm.py
samplics/sae/__init__.py
samplics/sae/eb_unit_model.py
samplics/sae/eblup_area_model.py
samplics/sae/eblup_unit_model.py
samplics/sae/robust_unit_model.py
samplics/sae/sae_core_functions.py
samplics/sampling/__init__.py
samplics/sampling/power_functions.py
samplics/sampling/selection.py
samplics/sampling/size.py
samplics/sampling/size_functions.py
samplics/types/__init__.py
samplics/types/basic.py
samplics/types/containers.py
samplics/types/errors.py
samplics/types/options.py
samplics/types/protocols.py
samplics/utils/__init__.py
samplics/utils/basic_functions.py
samplics/utils/checks.py
samplics/utils/errors.py
samplics/utils/formats.py
samplics/utils/hadamard.py
samplics/utils/types.py
samplics-0.4.55.dist-info/METADATA
samplics-0.4.55.dist-info/WHEEL
samplics-0.4.55.dist-info/RECORD
