Metadata-Version: 2.4
Name: samplics
Version: 0.4.55
Summary: Select, weight and analyze complex sample data
Project-URL: repository, https://github.com/survey-methods/samplics
Project-URL: documentation, https://samplics-org.github.io/samplics/
Project-URL: homepage, https://samplics-org.github.io/samplics//
Author-email: Mamadou S Diallo <msdiallo@samplics.org>
Keywords: estimation,sample,sampling,survey,weighting
Classifier: Development Status :: 4 - Beta
Classifier: Operating System :: OS Independent
Classifier: Programming Language :: Python :: 3.10
Classifier: Programming Language :: Python :: 3.11
Classifier: Programming Language :: Python :: 3.12
Classifier: Programming Language :: Python :: 3.13
Classifier: Programming Language :: Python :: Implementation :: CPython
Classifier: Topic :: Scientific/Engineering
Requires-Python: >=3.10
Requires-Dist: numpy>=2.1
Requires-Dist: polars[pyarrow]>=1.21.0
Requires-Dist: statsmodels>=0.14
